refgenconf/__init__.py
refgenconf/_version.py
refgenconf/const.py
refgenconf/exceptions.py
refgenconf/helpers.py
refgenconf/henge.py
refgenconf/populator.py
refgenconf/progress_bar.py
refgenconf/refgenconf.py
refgenconf/refgenconf_v03.py
refgenconf/seqcol.py
refgenconf/schemas/AnnotatedSequenceDigestList.yaml
refgenconf/schemas/AnnotatedSequenceList.yaml
refgenconf/schemas/genome_config_schema.yaml
refgenconf-0.12.2.dist-info/LICENSE.txt
refgenconf-0.12.2.dist-info/METADATA
refgenconf-0.12.2.dist-info/WHEEL
refgenconf-0.12.2.dist-info/top_level.txt
refgenconf-0.12.2.dist-info/RECORD
