Metadata-Version: 2.1
Name: refgenconf
Version: 0.12.2
Summary: A standardized configuration object for reference genome assemblies
Home-page: https://refgenie.databio.org
Author: Nathan Sheffield, Vince Reuter, Michal Stolarczyk
License: BSD2
Keywords: bioinformatics,sequencing,ngs
Platform: UNKNOWN
Classifier: Development Status :: 4 - Beta
Classifier: License :: OSI Approved :: BSD License
Classifier: Programming Language :: Python :: 3.5
Classifier: Programming Language :: Python :: 3.6
Classifier: Programming Language :: Python :: 3.7
Classifier: Programming Language :: Python :: 3.8
Classifier: Topic :: Scientific/Engineering :: Bio-Informatics
License-File: LICENSE.txt
